{"variables":[],"info":{"name":"","_postman_id":"8b394ce9-4ec1-4afd-92e4-68c6446983f8","description":"","schema":"https:\/\/schema.getpostman.com\/json\/collection\/v2.0.0\/collection.json"},"item":[{"name":"general","description":"","item":[{"name":"Einloggen","request":{"url":"http:\/\/project-zero.local\/api\/user\/login","method":"POST","body":{"mode":"formdata","formdata":[]},"description":"","response":[]}},{"name":"Account erstellen","request":{"url":"http:\/\/project-zero.local\/api\/user","method":"POST","body":{"mode":"formdata","formdata":[{"key":"name","value":"unde","type":"text","enabled":true},{"key":"email","value":"felipa52@example.org","type":"text","enabled":true},{"key":"password","value":"unde","type":"text","enabled":true}]},"description":"","response":[]}},{"name":"Liste aller User","request":{"url":"http:\/\/project-zero.local\/api\/users","method":"GET","body":{"mode":"formdata","formdata":[]},"description":"","response":[]}},{"name":"Account Informationen abrufen","request":{"url":"http:\/\/project-zero.local\/api\/user\/{id}","method":"GET","body":{"mode":"formdata","formdata":[]},"description":"","response":[]}},{"name":"Account Informationen abrufen","request":{"url":"http:\/\/project-zero.local\/api\/user","method":"GET","body":{"mode":"formdata","formdata":[]},"description":"","response":[]}},{"name":"Account Informationen updaten","request":{"url":"http:\/\/project-zero.local\/api\/user\/{id}","method":"PUT","body":{"mode":"formdata","formdata":[]},"description":"","response":[]}},{"name":"Account l\u00f6schen","request":{"url":"http:\/\/project-zero.local\/api\/user\/{id}","method":"DELETE","body":{"mode":"formdata","formdata":[]},"description":"","response":[]}},{"name":"Freundesliste","request":{"url":"http:\/\/project-zero.local\/api\/friends","method":"GET","body":{"mode":"formdata","formdata":[]},"description":"","response":[]}},{"name":"Freund hinzuf\u00fcgen","request":{"url":"http:\/\/project-zero.local\/api\/friend\/add","method":"POST","body":{"mode":"formdata","formdata":[{"key":"id","value":"illo","type":"text","enabled":true}]},"description":"","response":[]}},{"name":"Freund entfernen","request":{"url":"http:\/\/project-zero.local\/api\/friend\/remove\/{id}","method":"DELETE","body":{"mode":"formdata","formdata":[]},"description":"","response":[]}},{"name":"Alle Freundschaftsanfrage anzeigen","request":{"url":"http:\/\/project-zero.local\/api\/friend\/requests","method":"GET","body":{"mode":"formdata","formdata":[]},"description":"","response":[]}},{"name":"Freundschaftsanfrage akzeptieren","request":{"url":"http:\/\/project-zero.local\/api\/friend\/{request_id}\/accept","method":"GET","body":{"mode":"formdata","formdata":[]},"description":"","response":[]}},{"name":"Freundschaftsanfrage ablehnen","request":{"url":"http:\/\/project-zero.local\/api\/friend\/{request_id}\/decline","method":"GET","body":{"mode":"formdata","formdata":[]},"description":"","response":[]}},{"name":"Spiel erstellen","request":{"url":"http:\/\/project-zero.local\/api\/game","method":"POST","body":{"mode":"formdata","formdata":[{"key":"id_genre","value":"3","type":"text","enabled":true},{"key":"id_publisher","value":"2","type":"text","enabled":true},{"key":"name","value":"voluptatem","type":"text","enabled":true},{"key":"beschreibung","value":"voluptatem","type":"text","enabled":true}]},"description":"","response":[]}},{"name":"Spiele Liste abrufen","request":{"url":"http:\/\/project-zero.local\/api\/games","method":"GET","body":{"mode":"formdata","formdata":[]},"description":"","response":[]}},{"name":"Spiel Informationen abrufen","request":{"url":"http:\/\/project-zero.local\/api\/game\/{id}","method":"GET","body":{"mode":"formdata","formdata":[]},"description":"","response":[]}},{"name":"Spiel Informationen updaten","request":{"url":"http:\/\/project-zero.local\/api\/game\/{id}","method":"PUT","body":{"mode":"formdata","formdata":[]},"description":"","response":[]}},{"name":"Spiel l\u00f6schen","request":{"url":"http:\/\/project-zero.local\/api\/game\/{id}","method":"DELETE","body":{"mode":"formdata","formdata":[]},"description":"","response":[]}},{"name":"Publisher Liste abrufen","request":{"url":"http:\/\/project-zero.local\/api\/publisher","method":"GET","body":{"mode":"formdata","formdata":[]},"description":"","response":[]}},{"name":"Genre Liste abrufen","request":{"url":"http:\/\/project-zero.local\/api\/genre","method":"GET","body":{"mode":"formdata","formdata":[]},"description":"","response":[]}},{"name":"Account Spiel hinzuf\u00fcgen","request":{"url":"http:\/\/project-zero.local\/api\/user\/game\/add","method":"POST","body":{"mode":"formdata","formdata":[{"key":"id","value":"perferendis","type":"text","enabled":true}]},"description":"","response":[]}},{"name":"Account Spiel entfernen","request":{"url":"http:\/\/project-zero.local\/api\/user\/game\/remove\/{id}","method":"DELETE","body":{"mode":"formdata","formdata":[]},"description":"","response":[]}},{"name":"Account Spiele anzeigen","request":{"url":"http:\/\/project-zero.local\/api\/user\/game\/list","method":"GET","body":{"mode":"formdata","formdata":[]},"description":"","response":[]}},{"name":"http:\/\/project-zero.local\/api\/chatroom\/{user_id}","request":{"url":"http:\/\/project-zero.local\/api\/chatroom\/{user_id}","method":"GET","body":{"mode":"formdata","formdata":[]},"description":"","response":[]}},{"name":"http:\/\/project-zero.local\/api\/chatroom\/{chatroom_id}\/messages","request":{"url":"http:\/\/project-zero.local\/api\/chatroom\/{chatroom_id}\/messages","method":"GET","body":{"mode":"formdata","formdata":[]},"description":"","response":[]}},{"name":"http:\/\/project-zero.local\/api\/chatroom\/{chatroom_id}\/messages","request":{"url":"http:\/\/project-zero.local\/api\/chatroom\/{chatroom_id}\/messages","method":"POST","body":{"mode":"formdata","formdata":[]},"description":"","response":[]}},{"name":"Notiz erstellen","request":{"url":"http:\/\/project-zero.local\/api\/note","method":"POST","body":{"mode":"formdata","formdata":[{"key":"titel","value":"placeat","type":"text","enabled":true},{"key":"text","value":"placeat","type":"text","enabled":true}]},"description":"","response":[]}},{"name":"Alle Notizen vom Benutzer","request":{"url":"http:\/\/project-zero.local\/api\/notes","method":"GET","body":{"mode":"formdata","formdata":[]},"description":"","response":[]}},{"name":"Notiz get by id","request":{"url":"http:\/\/project-zero.local\/api\/note\/{id}","method":"GET","body":{"mode":"formdata","formdata":[]},"description":"","response":[]}},{"name":"Notiz updaten\/\u00e4ndern","request":{"url":"http:\/\/project-zero.local\/api\/note\/{id}","method":"PUT","body":{"mode":"formdata","formdata":[]},"description":"","response":[]}},{"name":"Notiz l\u00f6schen","request":{"url":"http:\/\/project-zero.local\/api\/note\/{id}","method":"DELETE","body":{"mode":"formdata","formdata":[]},"description":"","response":[]}},{"name":"Gruppe erstellen","request":{"url":"http:\/\/project-zero.local\/api\/group","method":"POST","body":{"mode":"formdata","formdata":[{"key":"name","value":"voluptas","type":"text","enabled":true},{"key":"beschreibung","value":"voluptas","type":"text","enabled":true}]},"description":"","response":[]}},{"name":"Gruppe by id","request":{"url":"http:\/\/project-zero.local\/api\/group\/{group_id}","method":"GET","body":{"mode":"formdata","formdata":[]},"description":"","response":[]}},{"name":"Gruppe User hinzuf\u00fcgen (anfrage)","request":{"url":"http:\/\/project-zero.local\/api\/group\/{group_id}\/add_user","method":"POST","body":{"mode":"formdata","formdata":[{"key":"id","value":"1","type":"text","enabled":true}]},"description":"","response":[]}},{"name":"Anfrage an Gruppe","request":{"url":"http:\/\/project-zero.local\/api\/group\/{group_id}\/request_access","method":"GET","body":{"mode":"formdata","formdata":[]},"description":"","response":[]}},{"name":"User entfernen auf Gruppe","request":{"url":"http:\/\/project-zero.local\/api\/group\/{group_id}\/remove_user","method":"POST","body":{"mode":"formdata","formdata":[{"key":"id","value":"1","type":"text","enabled":true}]},"description":"","response":[]}},{"name":"Alle Grupen Anfragen an User","request":{"url":"http:\/\/project-zero.local\/api\/user\/groups\/requests","method":"GET","body":{"mode":"formdata","formdata":[]},"description":"","response":[]}},{"name":"Gruppen Anfrage akzeptieren von Gruppe","request":{"url":"http:\/\/project-zero.local\/api\/user\/group\/{group_id}\/accept","method":"GET","body":{"mode":"formdata","formdata":[]},"description":"","response":[]}},{"name":"Gruppen Anfrage ablehnen von Gruppe","request":{"url":"http:\/\/project-zero.local\/api\/user\/group\/{group_id}\/decline","method":"GET","body":{"mode":"formdata","formdata":[]},"description":"","response":[]}},{"name":"Alle Grupen Anfragen an Gruppe","request":{"url":"http:\/\/project-zero.local\/api\/group\/{group_id}\/requests","method":"GET","body":{"mode":"formdata","formdata":[]},"description":"","response":[]}},{"name":"User Anfrage an Gruppe akzeptieren","request":{"url":"http:\/\/project-zero.local\/api\/group\/{group_id}\/accept\/{user_id}","method":"GET","body":{"mode":"formdata","formdata":[]},"description":"","response":[]}},{"name":"User Anfrage an Gruppe ablehnen","request":{"url":"http:\/\/project-zero.local\/api\/group\/{group_id}\/decline\/{user_id}","method":"GET","body":{"mode":"formdata","formdata":[]},"description":"","response":[]}},{"name":"Alle Gruppen eines Benutzers","request":{"url":"http:\/\/project-zero.local\/api\/user\/groups","method":"GET","body":{"mode":"formdata","formdata":[]},"description":"","response":[]}},{"name":"Alle Gruppen anzeigen","request":{"url":"http:\/\/project-zero.local\/api\/groups","method":"GET","body":{"mode":"formdata","formdata":[]},"description":"","response":[]}},{"name":"Gruppen l\u00f6schen","request":{"url":"http:\/\/project-zero.local\/api\/group\/{group_id}","method":"DELETE","body":{"mode":"formdata","formdata":[]},"description":"","response":[]}},{"name":"Gruppe Notiz hinzuf\u00fcgen","request":{"url":"http:\/\/project-zero.local\/api\/group\/{group_id}\/attach\/note\/{note_id}","method":"GET","body":{"mode":"formdata","formdata":[]},"description":"","response":[]}},{"name":"Gruppe Notiz entfernen","request":{"url":"http:\/\/project-zero.local\/api\/group\/{group_id}\/detach\/note\/{note_id}","method":"GET","body":{"mode":"formdata","formdata":[]},"description":"","response":[]}},{"name":"Alle Notizen einer Gruppe","request":{"url":"http:\/\/project-zero.local\/api\/group\/{group_id}\/notes","method":"GET","body":{"mode":"formdata","formdata":[]},"description":"","response":[]}}]}]}